pyvcon/__init__.py
pyvcon/client.py
pyvcon_async-0.1.0.dist-info/licenses/LICENSE
pyvcon_async-0.1.0.dist-info/METADATA
pyvcon_async-0.1.0.dist-info/WHEEL
pyvcon_async-0.1.0.dist-info/top_level.txt
pyvcon_async-0.1.0.dist-info/RECORD
