Metadata-Version: 2.4
Name: pyvcon-async
Version: 0.1.0
Summary: Minimal async RCON client for Pavlov VR and Source engine servers
Author: Your Name
Requires-Python: >=3.7
License-File: LICENSE
Dynamic: author
Dynamic: license-file
Dynamic: requires-python
Dynamic: summary
